SUMADORRESTADOR.v
module SUMADORRESTADOR (
    input [3:0] A,
    input [3:0] B,
    input OP,          // 0 = Suma, 1 = Resta
    output [3:0] RESULTADO,
    output COUT_EXT
);

    wire [3:0] B_XOR;
    wire c1, c2, c3;

    // Lógica XOR para invertir B solo si OP es 1
    assign B_XOR[0] = B[0] ^ OP;
    assign B_XOR[1] = B[1] ^ OP;
    assign B_XOR[2] = B[2] ^ OP;
    assign B_XOR[3] = B[3] ^ OP;

    // Instancias usando el módulo SUMADOR1BIT (que está definido abajo)
    SUMADOR1BIT bit0 (.A_IN(A[0]), .B_IN(B_XOR[0]), .C_IN(OP), .S1_OUT(RESULTADO[0]), .C1_OUT(c1));
    SUMADOR1BIT bit1 (.A_IN(A[1]), .B_IN(B_XOR[1]), .C_IN(c1), .S1_OUT(RESULTADO[1]), .C1_OUT(c2));
    SUMADOR1BIT bit2 (.A_IN(A[2]), .B_IN(B_XOR[2]), .C_IN(c2), .S1_OUT(RESULTADO[2]), .C1_OUT(c3));
    SUMADOR1BIT bit3 (.A_IN(A[3]), .B_IN(B_XOR[3]), .C_IN(c3), .S1_OUT(RESULTADO[3]), .C1_OUT(COUT_EXT));

endmodule 

// Módulo de 1 bit metido en el mismo archivo para no generar más códigos
module SUMADOR1BIT (
    input A_IN, B_IN, C_IN,
    output S1_OUT, C1_OUT
);
    assign S1_OUT = A_IN ^ B_IN ^ C_IN;
    assign C1_OUT = (A_IN & B_IN) | (C_IN & (A_IN ^ B_IN));
endmodule

SUMADORRESTADOR_tb.v
`timescale 1ns/1ps

module SUMADORRESTADOR_tb;
    reg [3:0] A_tb, B_tb;
    reg OP_tb;
    wire [3:0] RESULTADO_tb;
    wire COUT_EXT_tb;
    integer i, j;

    // Instancia del módulo unificado
    SUMADORRESTADOR uut (
        .A(A_tb), .B(B_tb), .OP(OP_tb), .RESULTADO(RESULTADO_tb), .COUT_EXT(COUT_EXT_tb)
    );

    initial begin
        $dumpfile("simulacion_total.vcd");
        $dumpvars(0, SUMADORRESTADOR_tb);

        // Prueba todas las combinaciones de SUMA
        OP_tb = 0;
        for(i=0; i<16; i=i+1) begin
            for(j=0; j<16; j=j+1) begin
                A_tb = i; B_tb = j; #5;
            end
        end

        // Prueba todas las combinaciones de RESTA
        OP_tb = 1;
        for(i=0; i<16; i=i+1) begin
            for(j=0; j<16; j=j+1) begin
                A_tb = i; B_tb = j; #5;
            end
        end

        $finish;
    end
endmodule

simulacion_total.vcd
$date
	Thu Mar 12 20:10:54 2026
$end
$version
	Icarus Verilog
$end
$timescale
	1ps
$end
$scope module SUMADORRESTADOR_tb $end
$var wire 4 ! RESULTADO_tb [3:0] $end
$var wire 1 " COUT_EXT_tb $end
$var reg 4 # A_tb [3:0] $end
$var reg 4 $ B_tb [3:0] $end
$var reg 1 % OP_tb $end
$var integer 32 & i [31:0] $end
$var integer 32 ' j [31:0] $end
$scope module uut $end
$var wire 4 ( A [3:0] $end
$var wire 4 ) B [3:0] $end
$var wire 1 % OP $end
$var wire 1 * c3 $end
$var wire 1 + c2 $end
$var wire 1 , c1 $end
$var wire 4 - RESULTADO [3:0] $end
$var wire 1 " COUT_EXT $end
$var wire 4 . B_XOR [3:0] $end
$scope module bit0 $end
$var wire 1 / A_IN $end
$var wire 1 0 B_IN $end
$var wire 1 , C1_OUT $end
$var wire 1 % C_IN $end
$var wire 1 1 S1_OUT $end
$upscope $end
$scope module bit1 $end
$var wire 1 2 A_IN $end
$var wire 1 3 B_IN $end
$var wire 1 + C1_OUT $end
$var wire 1 , C_IN $end
$var wire 1 4 S1_OUT $end
$upscope $end
$scope module bit2 $end
$var wire 1 5 A_IN $end
$var wire 1 6 B_IN $end
$var wire 1 * C1_OUT $end
$var wire 1 + C_IN $end
$var wire 1 7 S1_OUT $end
$upscope $end
$scope module bit3 $end
$var wire 1 8 A_IN $end
$var wire 1 9 B_IN $end
$var wire 1 " C1_OUT $end
$var wire 1 * C_IN $end
$var wire 1 : S1_OUT $end
$upscope $end
$upscope $end
$upscope $end
$enddefinitions $end
$comment Show the parameter values. $end
$dumpall
$end
#0
$dumpvars
0:
09
08
07
06
05
04
03
02
01
00
0/
b0 .
b0 -
0,
0+
0*
b0 )
b0 (
b0 '
b0 &
0%
b0 $
b0 #
0"
b0 !
$end
#5000
b1 !
b1 -
11
10
b1 .
b1 $
b1 )
b1 '
#10000
01
b10 !
b10 -
14
00
13
b10 .
b10 $
b10 )
b10 '
#15000
b11 !
b11 -
11
10
b11 .
b11 $
b11 )
b11 '
#20000
01
04
b100 !
b100 -
17
00
03
16
b100 .
b100 $
b100 )
b100 '
#25000
b101 !
b101 -
11
10
b101 .
b101 $
b101 )
b101 '
#30000
01
b110 !
b110 -
14
00
13
b110 .
b110 $
b110 )
b110 '
#35000
b111 !
b111 -
11
10
b111 .
b111 $
b111 )
b111 '
#40000
01
04
07
b1000 !
b1000 -
1:
00
03
06
19
b1000 .
b1000 $
b1000 )
b1000 '
#45000
b1001 !
b1001 -
11
10
b1001 .
b1001 $
b1001 )
b1001 '
#50000
01
b1010 !
b1010 -
14
00
13
b1010 .
b1010 $
b1010 )
b1010 '
#55000
b1011 !
b1011 -
11
10
b1011 .
b1011 $
b1011 )
b1011 '
#60000
01
04
b1100 !
b1100 -
17
00
03
16
b1100 .
b1100 $
b1100 )
b1100 '
#65000
b1101 !
b1101 -
11
10
b1101 .
b1101 $
b1101 )
b1101 '
#70000
01
b1110 !
b1110 -
14
00
13
b1110 .
b1110 $
b1110 )
b1110 '
#75000
b1111 !
b1111 -
11
10
b1111 .
b1111 $
b1111 )
b1111 '
#80000
07
0:
0+
04
00
03
06
09
b1 !
b1 -
11
0,
b0 .
1/
b0 $
b0 )
b1 #
b1 (
b1 &
b0 '
#85000
14
b10 !
b10 -
01
1,
10
b1 .
b1 $
b1 )
b1 '
#90000
07
0+
11
0,
b11 !
b11 -
14
00
13
b10 .
b10 $
b10 )
b10 '
#95000
17
1+
04
b100 !
b100 -
01
1,
10
b11 .
b11 $
b11 )
b11 '
#100000
0:
0+
0*
11
0,
04
b101 !
b101 -
17
00
03
16
b100 .
b100 $
b100 )
b100 '
#105000
14
b110 !
b110 -
01
1,
10
b101 .
b101 $
b101 )
b101 '
#110000
0:
0*
17
0+
11
0,
b111 !
b111 -
14
00
13
b110 .
b110 $
b110 )
b110 '
#115000
1:
1*
07
1+
04
b1000 !
b1000 -
01
1,
10
b111 .
b111 $
b111 )
b111 '
#120000
0+
0*
0"
11
0,
04
07
b1001 !
b1001 -
1:
00
03
06
19
b1000 .
b1000 $
b1000 )
b1000 '
#125000
14
b1010 !
b1010 -
01
1,
10
b1001 .
b1001 $
b1001 )
b1001 '
#130000
07
0+
11
0,
b1011 !
b1011 -
14
00
13
b1010 .
b1010 $
b1010 )
b1010 '
#135000
17
1+
04
b1100 !
b1100 -
01
1,
10
b1011 .
b1011 $
b1011 )
b1011 '
#140000
0"
1:
0+
0*
11
0,
04
b1101 !
b1101 -
17
00
03
16
b1100 .
b1100 $
b1100 )
b1100 '
#145000
14
b1110 !
b1110 -
01
1,
10
b1101 .
b1101 $
b1101 )
b1101 '
#150000
0"
1:
0*
17
0+
11
0,
b1111 !
b1111 -
14
00
13
b1110 .
b1110 $
b1110 )
b1110 '
#155000
1"
0:
1*
07
1+
04
b0 !
b0 -
01
1,
10
b1111 .
b1111 $
b1111 )
b1111 '
#160000
0*
0"
0+
07
0:
00
03
06
09
01
0,
b10 !
b10 -
14
b0 .
0/
12
b0 $
b0 )
b10 #
b10 (
b10 &
b0 '
#165000
b11 !
b11 -
11
10
b1 .
b1 $
b1 )
b1 '
#170000
17
01
b100 !
b100 -
04
1+
00
13
b10 .
b10 $
b10 )
b10 '
#175000
b101 !
b101 -
11
10
b11 .
b11 $
b11 )
b11 '
#180000
0:
0*
01
14
0+
b110 !
b110 -
17
00
03
16
b100 .
b100 $
b100 )
b100 '
#185000
b111 !
b111 -
11
10
b101 .
b101 $
b101 )
b101 '
#190000
1:
1*
07
01
b1000 !
b1000 -
04
1+
00
13
b110 .
b110 $
b110 )
b110 '
#195000
b1001 !
b1001 -
11
10
b111 .
b111 $
b111 )
b111 '
#200000
0*
0"
01
14
0+
07
b1010 !
b1010 -
1:
00
03
06
19
b1000 .
b1000 $
b1000 )
b1000 '
#205000
b1011 !
b1011 -
11
10
b1001 .
b1001 $
b1001 )
b1001 '
#210000
17
01
b1100 !
b1100 -
04
1+
00
13
b1010 .
b1010 $
b1010 )
b1010 '
#215000
b1101 !
b1101 -
11
10
b1011 .
b1011 $
b1011 )
b1011 '
#220000
0"
1:
0*
01
14
0+
b1110 !
b1110 -
17
00
03
16
b1100 .
b1100 $
b1100 )
b1100 '
#225000
b1111 !
b1111 -
11
10
b1101 .
b1101 $
b1101 )
b1101 '
#230000
1"
0:
1*
07
01
b0 !
b0 -
04
1+
00
13
b1110 .
b1110 $
b1110 )
b1110 '
#235000
b1 !
b1 -
11
10
b1111 .
b1111 $
b1111 )
b1111 '
#240000
0+
0*
0"
07
0:
14
00
03
06
09
b11 !
b11 -
11
0,
b0 .
1/
b0 $
b0 )
b11 #
b11 (
b11 &
b0 '
#245000
17
1+
04
b100 !
b100 -
01
1,
10
b1 .
b1 $
b1 )
b1 '
#250000
11
0,
b101 !
b101 -
04
00
13
b10 .
b10 $
b10 )
b10 '
#255000
14
b110 !
b110 -
01
1,
10
b11 .
b11 $
b11 )
b11 '
#260000
0+
0:
0*
11
0,
14
b111 !
b111 -
17
00
03
16
b100 .
b100 $
b100 )
b100 '
#265000
1:
1*
07
1+
04
b1000 !
b1000 -
01
1,
10
b101 .
b101 $
b101 )
b101 '
#270000
11
0,
b1001 !
b1001 -
04
00
13
b110 .
b110 $
b110 )
b110 '
#275000
14
b1010 !
b1010 -
01
1,
10
b111 .
b111 $
b111 )
b111 '
#280000
0+
0*
0"
11
0,
14
07
b1011 !
b1011 -
1:
00
03
06
19
b1000 .
b1000 $
b1000 )
b1000 '
#285000
17
1+
04
b1100 !
b1100 -
01
1,
10
b1001 .
b1001 $
b1001 )
b1001 '
#290000
11
0,
b1101 !
b1101 -
04
00
13
b1010 .
b1010 $
b1010 )
b1010 '
#295000
14
b1110 !
b1110 -
01
1,
10
b1011 .
b1011 $
b1011 )
b1011 '
#300000
0"
0+
1:
0*
11
0,
14
b1111 !
b1111 -
17
00
03
16
b1100 .
b1100 $
b1100 )
b1100 '
#305000
1"
0:
1*
07
1+
04
b0 !
b0 -
01
1,
10
b1101 .
b1101 $
b1101 )
b1101 '
#310000
11
0,
b1 !
b1 -
04
00
13
b1110 .
b1110 $
b1110 )
b1110 '
#315000
14
b10 !
b10 -
01
1,
10
b1111 .
b1111 $
b1111 )
b1111 '
#320000
0"
0*
0:
0+
00
03
06
09
01
0,
04
b100 !
b100 -
17
b0 .
0/
02
15
b0 $
b0 )
b100 #
b100 (
b100 &
b0 '
#325000
b101 !
b101 -
11
10
b1 .
b1 $
b1 )
b1 '
#330000
01
b110 !
b110 -
14
00
13
b10 .
b10 $
b10 )
b10 '
#335000
b111 !
b111 -
11
10
b11 .
b11 $
b11 )
b11 '
#340000
1:
01
04
b1000 !
b1000 -
07
1*
00
03
16
b100 .
b100 $
b100 )
b100 '
#345000
b1001 !
b1001 -
11
10
b101 .
b101 $
b101 )
b101 '
#350000
01
b1010 !
b1010 -
14
00
13
b110 .
b110 $
b110 )
b110 '
#355000
b1011 !
b1011 -
11
10
b111 .
b111 $
b111 )
b111 '
#360000
0"
01
04
17
0*
b1100 !
b1100 -
1:
00
03
06
19
b1000 .
b1000 $
b1000 )
b1000 '
#365000
b1101 !
b1101 -
11
10
b1001 .
b1001 $
b1001 )
b1001 '
#370000
01
b1110 !
b1110 -
14
00
13
b1010 .
b1010 $
b1010 )
b1010 '
#375000
b1111 !
b1111 -
11
10
b1011 .
b1011 $
b1011 )
b1011 '
#380000
1"
0:
01
04
b0 !
b0 -
07
1*
00
03
16
b1100 .
b1100 $
b1100 )
b1100 '
#385000
b1 !
b1 -
11
10
b1101 .
b1101 $
b1101 )
b1101 '
#390000
01
b10 !
b10 -
14
00
13
b1110 .
b1110 $
b1110 )
b1110 '
#395000
b11 !
b11 -
11
10
b1111 .
b1111 $
b1111 )
b1111 '
#400000
0*
17
0"
0:
0+
04
00
03
06
09
b101 !
b101 -
11
0,
b0 .
1/
b0 $
b0 )
b101 #
b101 (
b101 &
b0 '
#405000
14
b110 !
b110 -
01
1,
10
b1 .
b1 $
b1 )
b1 '
#410000
0:
0*
17
0+
11
0,
b111 !
b111 -
14
00
13
b10 .
b10 $
b10 )
b10 '
#415000
1:
1*
07
1+
04
b1000 !
b1000 -
01
1,
10
b11 .
b11 $
b11 )
b11 '
#420000
0+
11
0,
04
b1001 !
b1001 -
07
00
03
16
b100 .
b100 $
b100 )
b100 '
#425000
14
b1010 !
b1010 -
01
1,
10
b101 .
b101 $
b101 )
b101 '
#430000
07
0+
11
0,
b1011 !
b1011 -
14
00
13
b110 .
b110 $
b110 )
b110 '
#435000
17
1+
04
b1100 !
b1100 -
01
1,
10
b111 .
b111 $
b111 )
b111 '
#440000
0*
0+
0"
11
0,
04
17
b1101 !
b1101 -
1:
00
03
06
19
b1000 .
b1000 $
b1000 )
b1000 '
#445000
14
b1110 !
b1110 -
01
1,
10
b1001 .
b1001 $
b1001 )
b1001 '
#450000
0"
1:
0*
17
0+
11
0,
b1111 !
b1111 -
14
00
13
b1010 .
b1010 $
b1010 )
b1010 '
#455000
1"
0:
1*
07
1+
04
b0 !
b0 -
01
1,
10
b1011 .
b1011 $
b1011 )
b1011 '
#460000
0+
11
0,
04
b1 !
b1 -
07
00
03
16
b1100 .
b1100 $
b1100 )
b1100 '
#465000
14
b10 !
b10 -
01
1,
10
b1101 .
b1101 $
b1101 )
b1101 '
#470000
07
0+
11
0,
b11 !
b11 -
14
00
13
b1110 .
b1110 $
b1110 )
b1110 '
#475000
17
1+
04
b100 !
b100 -
01
1,
10
b1111 .
b1111 $
b1111 )
b1111 '
#480000
0*
0"
0+
17
0:
00
03
06
09
01
0,
b110 !
b110 -
14
b0 .
0/
12
b0 $
b0 )
b110 #
b110 (
b110 &
b0 '
#485000
b111 !
b111 -
11
10
b1 .
b1 $
b1 )
b1 '
#490000
1:
1*
07
01
b1000 !
b1000 -
04
1+
00
13
b10 .
b10 $
b10 )
b10 '
#495000
b1001 !
b1001 -
11
10
b11 .
b11 $
b11 )
b11 '
#500000
01
14
0+
b1010 !
b1010 -
07
00
03
16
b100 .
b100 $
b100 )
b100 '
#505000
b1011 !
b1011 -
11
10
b101 .
b101 $
b101 )
b101 '
#510000
17
01
b1100 !
b1100 -
04
1+
00
13
b110 .
b110 $
b110 )
b110 '
#515000
b1101 !
b1101 -
11
10
b111 .
b111 $
b111 )
b111 '
#520000
0*
0"
01
14
0+
17
b1110 !
b1110 -
1:
00
03
06
19
b1000 .
b1000 $
b1000 )
b1000 '
#525000
b1111 !
b1111 -
11
10
b1001 .
b1001 $
b1001 )
b1001 '
#530000
1"
0:
1*
07
01
b0 !
b0 -
04
1+
00
13
b1010 .
b1010 $
b1010 )
b1010 '
#535000
b1 !
b1 -
11
10
b1011 .
b1011 $
b1011 )
b1011 '
#540000
01
14
0+
b10 !
b10 -
07
00
03
16
b1100 .
b1100 $
b1100 )
b1100 '
#545000
b11 !
b11 -
11
10
b1101 .
b1101 $
b1101 )
b1101 '
#550000
17
01
b100 !
b100 -
04
1+
00
13
b1110 .
b1110 $
b1110 )
b1110 '
#555000
b101 !
b101 -
11
10
b1111 .
b1111 $
b1111 )
b1111 '
#560000
0*
0+
0"
17
0:
14
00
03
06
09
b111 !
b111 -
11
0,
b0 .
1/
b0 $
b0 )
b111 #
b111 (
b111 &
b0 '
#565000
1:
1*
07
1+
04
b1000 !
b1000 -
01
1,
10
b1 .
b1 $
b1 )
b1 '
#570000
11
0,
b1001 !
b1001 -
04
00
13
b10 .
b10 $
b10 )
b10 '
#575000
14
b1010 !
b1010 -
01
1,
10
b11 .
b11 $
b11 )
b11 '
#580000
0+
11
0,
14
b1011 !
b1011 -
07
00
03
16
b100 .
b100 $
b100 )
b100 '
#585000
17
1+
04
b1100 !
b1100 -
01
1,
10
b101 .
b101 $
b101 )
b101 '
#590000
11
0,
b1101 !
b1101 -
04
00
13
b110 .
b110 $
b110 )
b110 '
#595000
14
b1110 !
b1110 -
01
1,
10
b111 .
b111 $
b111 )
b111 '
#600000
0*
0+
0"
11
0,
14
17
b1111 !
b1111 -
1:
00
03
06
19
b1000 .
b1000 $
b1000 )
b1000 '
#605000
1"
0:
1*
07
1+
04
b0 !
b0 -
01
1,
10
b1001 .
b1001 $
b1001 )
b1001 '
#610000
11
0,
b1 !
b1 -
04
00
13
b1010 .
b1010 $
b1010 )
b1010 '
#615000
14
b10 !
b10 -
01
1,
10
b1011 .
b1011 $
b1011 )
b1011 '
#620000
0+
11
0,
14
b11 !
b11 -
07
00
03
16
b1100 .
b1100 $
b1100 )
b1100 '
#625000
17
1+
04
b100 !
b100 -
01
1,
10
b1101 .
b1101 $
b1101 )
b1101 '
#630000
11
0,
b101 !
b101 -
04
00
13
b1110 .
b1110 $
b1110 )
b1110 '
#635000
14
b110 !
b110 -
01
1,
10
b1111 .
b1111 $
b1111 )
b1111 '
#640000
0"
0*
0+
00
03
06
09
01
0,
04
07
b1000 !
b1000 -
1:
b0 .
0/
02
05
18
b0 $
b0 )
b1000 #
b1000 (
b1000 &
b0 '
#645000
b1001 !
b1001 -
11
10
b1 .
b1 $
b1 )
b1 '
#650000
01
b1010 !
b1010 -
14
00
13
b10 .
b10 $
b10 )
b10 '
#655000
b1011 !
b1011 -
11
10
b11 .
b11 $
b11 )
b11 '
#660000
01
04
b1100 !
b1100 -
17
00
03
16
b100 .
b100 $
b100 )
b100 '
#665000
b1101 !
b1101 -
11
10
b101 .
b101 $
b101 )
b101 '
#670000
01
b1110 !
b1110 -
14
00
13
b110 .
b110 $
b110 )
b110 '
#675000
b1111 !
b1111 -
11
10
b111 .
b111 $
b111 )
b111 '
#680000
01
04
07
b0 !
b0 -
0:
1"
00
03
06
19
b1000 .
b1000 $
b1000 )
b1000 '
#685000
b1 !
b1 -
11
10
b1001 .
b1001 $
b1001 )
b1001 '
#690000
01
b10 !
b10 -
14
00
13
b1010 .
b1010 $
b1010 )
b1010 '
#695000
b11 !
b11 -
11
10
b1011 .
b1011 $
b1011 )
b1011 '
#700000
01
04
b100 !
b100 -
17
00
03
16
b1100 .
b1100 $
b1100 )
b1100 '
#705000
b101 !
b101 -
11
10
b1101 .
b1101 $
b1101 )
b1101 '
#710000
01
b110 !
b110 -
14
00
13
b1110 .
b1110 $
b1110 )
b1110 '
#715000
b111 !
b111 -
11
10
b1111 .
b1111 $
b1111 )
b1111 '
#720000
07
1:
0"
0+
04
00
03
06
09
b1001 !
b1001 -
11
0,
b0 .
1/
b0 $
b0 )
b1001 #
b1001 (
b1001 &
b0 '
#725000
14
b1010 !
b1010 -
01
1,
10
b1 .
b1 $
b1 )
b1 '
#730000
07
0+
11
0,
b1011 !
b1011 -
14
00
13
b10 .
b10 $
b10 )
b10 '
#735000
17
1+
04
b1100 !
b1100 -
01
1,
10
b11 .
b11 $
b11 )
b11 '
#740000
0"
1:
0+
0*
11
0,
04
b1101 !
b1101 -
17
00
03
16
b100 .
b100 $
b100 )
b100 '
#745000
14
b1110 !
b1110 -
01
1,
10
b101 .
b101 $
b101 )
b101 '
#750000
0"
1:
0*
17
0+
11
0,
b1111 !
b1111 -
14
00
13
b110 .
b110 $
b110 )
b110 '
#755000
1"
0:
1*
07
1+
04
b0 !
b0 -
01
1,
10
b111 .
b111 $
b111 )
b111 '
#760000
0+
0*
11
0,
04
07
b1 !
b1 -
0:
00
03
06
19
b1000 .
b1000 $
b1000 )
b1000 '
#765000
14
b10 !
b10 -
01
1,
10
b1001 .
b1001 $
b1001 )
b1001 '
#770000
07
0+
11
0,
b11 !
b11 -
14
00
13
b1010 .
b1010 $
b1010 )
b1010 '
#775000
17
1+
04
b100 !
b100 -
01
1,
10
b1011 .
b1011 $
b1011 )
b1011 '
#780000
0:
0+
0*
11
0,
04
b101 !
b101 -
17
00
03
16
b1100 .
b1100 $
b1100 )
b1100 '
#785000
14
b110 !
b110 -
01
1,
10
b1101 .
b1101 $
b1101 )
b1101 '
#790000
0:
0*
17
0+
11
0,
b111 !
b111 -
14
00
13
b1110 .
b1110 $
b1110 )
b1110 '
#795000
1:
1*
07
1+
04
b1000 !
b1000 -
01
1,
10
b1111 .
b1111 $
b1111 )
b1111 '
#800000
0"
0*
0+
07
1:
00
03
06
09
01
0,
b1010 !
b1010 -
14
b0 .
0/
12
b0 $
b0 )
b1010 #
b1010 (
b1010 &
b0 '
#805000
b1011 !
b1011 -
11
10
b1 .
b1 $
b1 )
b1 '
#810000
17
01
b1100 !
b1100 -
04
1+
00
13
b10 .
b10 $
b10 )
b10 '
#815000
b1101 !
b1101 -
11
10
b11 .
b11 $
b11 )
b11 '
#820000
0"
1:
0*
01
14
0+
b1110 !
b1110 -
17
00
03
16
b100 .
b100 $
b100 )
b100 '
#825000
b1111 !
b1111 -
11
10
b101 .
b101 $
b101 )
b101 '
#830000
1"
0:
1*
07
01
b0 !
b0 -
04
1+
00
13
b110 .
b110 $
b110 )
b110 '
#835000
b1 !
b1 -
11
10
b111 .
b111 $
b111 )
b111 '
#840000
0*
01
14
0+
07
b10 !
b10 -
0:
00
03
06
19
b1000 .
b1000 $
b1000 )
b1000 '
#845000
b11 !
b11 -
11
10
b1001 .
b1001 $
b1001 )
b1001 '
#850000
17
01
b100 !
b100 -
04
1+
00
13
b1010 .
b1010 $
b1010 )
b1010 '
#855000
b101 !
b101 -
11
10
b1011 .
b1011 $
b1011 )
b1011 '
#860000
0:
0*
01
14
0+
b110 !
b110 -
17
00
03
16
b1100 .
b1100 $
b1100 )
b1100 '
#865000
b111 !
b111 -
11
10
b1101 .
b1101 $
b1101 )
b1101 '
#870000
1:
1*
07
01
b1000 !
b1000 -
04
1+
00
13
b1110 .
b1110 $
b1110 )
b1110 '
#875000
b1001 !
b1001 -
11
10
b1111 .
b1111 $
b1111 )
b1111 '
#880000
0"
0+
0*
07
1:
14
00
03
06
09
b1011 !
b1011 -
11
0,
b0 .
1/
b0 $
b0 )
b1011 #
b1011 (
b1011 &
b0 '
#885000
17
1+
04
b1100 !
b1100 -
01
1,
10
b1 .
b1 $
b1 )
b1 '
#890000
11
0,
b1101 !
b1101 -
04
00
13
b10 .
b10 $
b10 )
b10 '
#895000
14
b1110 !
b1110 -
01
1,
10
b11 .
b11 $
b11 )
b11 '
#900000
0"
0+
1:
0*
11
0,
14
b1111 !
b1111 -
17
00
03
16
b100 .
b100 $
b100 )
b100 '
#905000
1"
0:
1*
07
1+
04
b0 !
b0 -
01
1,
10
b101 .
b101 $
b101 )
b101 '
#910000
11
0,
b1 !
b1 -
04
00
13
b110 .
b110 $
b110 )
b110 '
#915000
14
b10 !
b10 -
01
1,
10
b111 .
b111 $
b111 )
b111 '
#920000
0+
0*
11
0,
14
07
b11 !
b11 -
0:
00
03
06
19
b1000 .
b1000 $
b1000 )
b1000 '
#925000
17
1+
04
b100 !
b100 -
01
1,
10
b1001 .
b1001 $
b1001 )
b1001 '
#930000
11
0,
b101 !
b101 -
04
00
13
b1010 .
b1010 $
b1010 )
b1010 '
#935000
14
b110 !
b110 -
01
1,
10
b1011 .
b1011 $
b1011 )
b1011 '
#940000
0+
0:
0*
11
0,
14
b111 !
b111 -
17
00
03
16
b1100 .
b1100 $
b1100 )
b1100 '
#945000
1:
1*
07
1+
04
b1000 !
b1000 -
01
1,
10
b1101 .
b1101 $
b1101 )
b1101 '
#950000
11
0,
b1001 !
b1001 -
04
00
13
b1110 .
b1110 $
b1110 )
b1110 '
#955000
14
b1010 !
b1010 -
01
1,
10
b1111 .
b1111 $
b1111 )
b1111 '
#960000
0"
0*
1:
0+
00
03
06
09
01
0,
04
b1100 !
b1100 -
17
b0 .
0/
02
15
b0 $
b0 )
b1100 #
b1100 (
b1100 &
b0 '
#965000
b1101 !
b1101 -
11
10
b1 .
b1 $
b1 )
b1 '
#970000
01
b1110 !
b1110 -
14
00
13
b10 .
b10 $
b10 )
b10 '
#975000
b1111 !
b1111 -
11
10
b11 .
b11 $
b11 )
b11 '
#980000
1"
0:
01
04
b0 !
b0 -
07
1*
00
03
16
b100 .
b100 $
b100 )
b100 '
#985000
b1 !
b1 -
11
10
b101 .
b101 $
b101 )
b101 '
#990000
01
b10 !
b10 -
14
00
13
b110 .
b110 $
b110 )
b110 '
#995000
b11 !
b11 -
11
10
b111 .
b111 $
b111 )
b111 '
#1000000
01
04
17
0*
b100 !
b100 -
0:
00
03
06
19
b1000 .
b1000 $
b1000 )
b1000 '
#1005000
b101 !
b101 -
11
10
b1001 .
b1001 $
b1001 )
b1001 '
#1010000
01
b110 !
b110 -
14
00
13
b1010 .
b1010 $
b1010 )
b1010 '
#1015000
b111 !
b111 -
11
10
b1011 .
b1011 $
b1011 )
b1011 '
#1020000
1:
01
04
b1000 !
b1000 -
07
1*
00
03
16
b1100 .
b1100 $
b1100 )
b1100 '
#1025000
b1001 !
b1001 -
11
10
b1101 .
b1101 $
b1101 )
b1101 '
#1030000
01
b1010 !
b1010 -
14
00
13
b1110 .
b1110 $
b1110 )
b1110 '
#1035000
b1011 !
b1011 -
11
10
b1111 .
b1111 $
b1111 )
b1111 '
#1040000
0"
0*
17
1:
0+
04
00
03
06
09
b1101 !
b1101 -
11
0,
b0 .
1/
b0 $
b0 )
b1101 #
b1101 (
b1101 &
b0 '
#1045000
14
b1110 !
b1110 -
01
1,
10
b1 .
b1 $
b1 )
b1 '
#1050000
0"
1:
0*
17
0+
11
0,
b1111 !
b1111 -
14
00
13
b10 .
b10 $
b10 )
b10 '
#1055000
1"
0:
1*
07
1+
04
b0 !
b0 -
01
1,
10
b11 .
b11 $
b11 )
b11 '
#1060000
0+
11
0,
04
b1 !
b1 -
07
00
03
16
b100 .
b100 $
b100 )
b100 '
#1065000
14
b10 !
b10 -
01
1,
10
b101 .
b101 $
b101 )
b101 '
#1070000
07
0+
11
0,
b11 !
b11 -
14
00
13
b110 .
b110 $
b110 )
b110 '
#1075000
17
1+
04
b100 !
b100 -
01
1,
10
b111 .
b111 $
b111 )
b111 '
#1080000
0*
0+
11
0,
04
17
b101 !
b101 -
0:
00
03
06
19
b1000 .
b1000 $
b1000 )
b1000 '
#1085000
14
b110 !
b110 -
01
1,
10
b1001 .
b1001 $
b1001 )
b1001 '
#1090000
0:
0*
17
0+
11
0,
b111 !
b111 -
14
00
13
b1010 .
b1010 $
b1010 )
b1010 '
#1095000
1:
1*
07
1+
04
b1000 !
b1000 -
01
1,
10
b1011 .
b1011 $
b1011 )
b1011 '
#1100000
0+
11
0,
04
b1001 !
b1001 -
07
00
03
16
b1100 .
b1100 $
b1100 )
b1100 '
#1105000
14
b1010 !
b1010 -
01
1,
10
b1101 .
b1101 $
b1101 )
b1101 '
#1110000
07
0+
11
0,
b1011 !
b1011 -
14
00
13
b1110 .
b1110 $
b1110 )
b1110 '
#1115000
17
1+
04
b1100 !
b1100 -
01
1,
10
b1111 .
b1111 $
b1111 )
b1111 '
#1120000
0"
0*
0+
17
1:
00
03
06
09
01
0,
b1110 !
b1110 -
14
b0 .
0/
12
b0 $
b0 )
b1110 #
b1110 (
b1110 &
b0 '
#1125000
b1111 !
b1111 -
11
10
b1 .
b1 $
b1 )
b1 '
#1130000
1"
0:
1*
07
01
b0 !
b0 -
04
1+
00
13
b10 .
b10 $
b10 )
b10 '
#1135000
b1 !
b1 -
11
10
b11 .
b11 $
b11 )
b11 '
#1140000
01
14
0+
b10 !
b10 -
07
00
03
16
b100 .
b100 $
b100 )
b100 '
#1145000
b11 !
b11 -
11
10
b101 .
b101 $
b101 )
b101 '
#1150000
17
01
b100 !
b100 -
04
1+
00
13
b110 .
b110 $
b110 )
b110 '
#1155000
b101 !
b101 -
11
10
b111 .
b111 $
b111 )
b111 '
#1160000
0*
01
14
0+
17
b110 !
b110 -
0:
00
03
06
19
b1000 .
b1000 $
b1000 )
b1000 '
#1165000
b111 !
b111 -
11
10
b1001 .
b1001 $
b1001 )
b1001 '
#1170000
1:
1*
07
01
b1000 !
b1000 -
04
1+
00
13
b1010 .
b1010 $
b1010 )
b1010 '
#1175000
b1001 !
b1001 -
11
10
b1011 .
b1011 $
b1011 )
b1011 '
#1180000
01
14
0+
b1010 !
b1010 -
07
00
03
16
b1100 .
b1100 $
b1100 )
b1100 '
#1185000
b1011 !
b1011 -
11
10
b1101 .
b1101 $
b1101 )
b1101 '
#1190000
17
01
b1100 !
b1100 -
04
1+
00
13
b1110 .
b1110 $
b1110 )
b1110 '
#1195000
b1101 !
b1101 -
11
10
b1111 .
b1111 $
b1111 )
b1111 '
#1200000
0"
0*
0+
17
1:
14
00
03
06
09
b1111 !
b1111 -
11
0,
b0 .
1/
b0 $
b0 )
b1111 #
b1111 (
b1111 &
b0 '
#1205000
1"
0:
1*
07
1+
04
b0 !
b0 -
01
1,
10
b1 .
b1 $
b1 )
b1 '
#1210000
11
0,
b1 !
b1 -
04
00
13
b10 .
b10 $
b10 )
b10 '
#1215000
14
b10 !
b10 -
01
1,
10
b11 .
b11 $
b11 )
b11 '
#1220000
0+
11
0,
14
b11 !
b11 -
07
00
03
16
b100 .
b100 $
b100 )
b100 '
#1225000
17
1+
04
b100 !
b100 -
01
1,
10
b101 .
b101 $
b101 )
b101 '
#1230000
11
0,
b101 !
b101 -
04
00
13
b110 .
b110 $
b110 )
b110 '
#1235000
14
b110 !
b110 -
01
1,
10
b111 .
b111 $
b111 )
b111 '
